spaceone/__init__.py
spaceone/repository/__init__.py
spaceone/repository/api/__init__.py
spaceone/repository/api/v1/__init__.py
spaceone/repository/api/v1/plugin.py
spaceone/repository/api/v1/policy.py
spaceone/repository/api/v1/repository.py
spaceone/repository/api/v1/schema.py
spaceone/repository/conf/__init__.py
spaceone/repository/conf/global_conf.py
spaceone/repository/conf/proto_conf.py
spaceone/repository/connector/__init__.py
spaceone/repository/connector/registry_connector.py
spaceone/repository/connector/remote_repository_connector.py
spaceone/repository/error/__init__.py
spaceone/repository/error/plugin.py
spaceone/repository/error/policy.py
spaceone/repository/error/repository.py
spaceone/repository/error/schema.py
spaceone/repository/info/__init__.py
spaceone/repository/info/common_info.py
spaceone/repository/info/plugin_info.py
spaceone/repository/info/policy_info.py
spaceone/repository/info/repository_info.py
spaceone/repository/info/schema_info.py
spaceone/repository/managed_resource/plugin/plugin-api-direct-mon-webhook.yaml
spaceone/repository/managed_resource/plugin/plugin-aws-cloud-service-inven-collector.yaml
spaceone/repository/managed_resource/plugin/plugin-aws-cloudtrail-mon-datasource.yaml
spaceone/repository/managed_resource/plugin/plugin-aws-cloudwatch-mon-datasource.yaml
spaceone/repository/managed_resource/plugin/plugin-aws-cost-explorer-cost-datasource.yaml
spaceone/repository/managed_resource/plugin/plugin-aws-ec2-inven-collector.yaml
spaceone/repository/managed_resource/plugin/plugin-aws-phd-inven-collector.yaml
spaceone/repository/managed_resource/plugin/plugin-aws-sns-mon-webhook.yaml
spaceone/repository/managed_resource/plugin/plugin-aws-trusted-advisor-inven-collector.yaml
spaceone/repository/managed_resource/plugin/plugin-azure-activity-log-mon-datasource.yaml
spaceone/repository/managed_resource/plugin/plugin-azure-cost-mgmt-cost-datasource.yaml
spaceone/repository/managed_resource/plugin/plugin-azure-inven-collector.yaml
spaceone_repository-1.12.5.dist-info/METADATA
spaceone_repository-1.12.5.dist-info/WHEEL
spaceone_repository-1.12.5.dist-info/top_level.txt
spaceone_repository-1.12.5.dist-info/RECORD
