Metadata-Version: 2.1
Name: spaceone-repository
Version: 1.12.5
Summary: SpaceONE repository service
Home-page: https://www.spaceone.dev/
Author: MEGAZONE SpaceONE Team
Author-email: admin@spaceone.dev
License: Apache License 2.0
Platform: UNKNOWN
Requires-Dist: spaceone-core
Requires-Dist: spaceone-api
Requires-Dist: mongoengine
Requires-Dist: python-consul
Requires-Dist: schematics
Requires-Dist: boto3
Requires-Dist: requests
Requires-Dist: redis
Requires-Dist: pandas
Requires-Dist: jsonschema
